modmanager/__init__.py
modmanager/mod_manager.py
modmanager/utils.py
modimportmanager-0.1.0.dist-info/LICENSE.txt
modimportmanager-0.1.0.dist-info/METADATA
modimportmanager-0.1.0.dist-info/WHEEL
modimportmanager-0.1.0.dist-info/top_level.txt
modimportmanager-0.1.0.dist-info/RECORD
