Metadata-Version: 2.2
Name: modimportmanager
Version: 0.1.0
Summary: A Python package that simplifies import management.
Author: Syed Sadiq
Author-email: syedsadiq201415@gmail.com
Requires-Python: >=3.7
License-File: LICENSE.txt
Dynamic: author
Dynamic: author-email
Dynamic: description
Dynamic: description-content-type
Dynamic: requires-python
Dynamic: summary
